evograd/__init__.py
evograd/distributions.py
evograd/expectation.py
evograd/noise.py
evograd-0.1.2.dist-info/LICENSE
evograd-0.1.2.dist-info/METADATA
evograd-0.1.2.dist-info/WHEEL
evograd-0.1.2.dist-info/top_level.txt
evograd-0.1.2.dist-info/RECORD
