Metadata-Version: 2.1
Name: evograd
Version: 0.1.2
Summary: A lightweight tool for differentiating through expectations
Home-page: https://github.com/uber-research/EvoGrad
Author: Alex Gajewski
Author-email: agajews@gmail.com
License: UNKNOWN
Platform: UNKNOWN
Classifier: Programming Language :: Python :: 3
Classifier: License :: OSI Approved :: MIT License
Classifier: Operating System :: OS Independent
Requires-Dist: numpy
Requires-Dist: torch
